pycommon/__init__.py
pycommon/csvutil.py
pycommon/decorators.py
pycommon/experimental.py
pycommon/fileutil.py
pycommon/hash.py
pycommon/http.py
pycommon/procutil.py
pycommon/testutil.py
pycommon/util.py
pycommon-0.3.6.dist-info/LICENSE.txt
pycommon-0.3.6.dist-info/METADATA
pycommon-0.3.6.dist-info/WHEEL
pycommon-0.3.6.dist-info/top_level.txt
pycommon-0.3.6.dist-info/RECORD
