Metadata-Version: 2.1
Name: pycommon
Version: 0.3.6
Summary: Useful functions missing from the standard libraries
Home-page: https://github.com/dgrant/pycommon
Author: David Grant
Author-email: davidgrant@gmail.com
License: UNKNOWN
Download-URL: https://github.com/dgrant/pycommon/tarball/0.3.6
Keywords: utility,miscellaneous,library
Platform: UNKNOWN
